LICENSE
MANIFEST.in
README.rst
setup.py
src/peltak_alembic/__init__.py
src/peltak_alembic/impl.py
src/peltak_alembic.egg-info/PKG-INFO
src/peltak_alembic.egg-info/SOURCES.txt
src/peltak_alembic.egg-info/dependency_links.txt
src/peltak_alembic.egg-info/requires.txt
src/peltak_alembic.egg-info/top_level.txt