Metadata-Version: 1.1
Name: peltak-alembic
Version: 0.0.1
Summary: peltak commands for alembic migrations
Home-page: http://github.com/novopl/peltak-alembic
Author: Mateusz 'novo' Klos
Author-email: novopl@gmail.com
License: Apache 2.0
Keywords: peltak dev ops devops
Platform: UNKNOWN
Classifier: Development Status :: 4 - Beta
Classifier: Topic :: Utilities
Classifier: Intended Audience :: Developers
Classifier: Programming Language :: Python
Classifier: License :: OSI Approved :: MIT License
